setup.py
retpy/__init__.py
retpy.egg-info/PKG-INFO
retpy.egg-info/SOURCES.txt
retpy.egg-info/dependency_links.txt
retpy.egg-info/not-zip-safe
retpy.egg-info/top_level.txt