Metadata-Version: 1.0
Name: retpy
Version: 0.1
Summary: Coming Soon
Home-page: http://retpy.org
Author: Erik Paulson
Author-email: epaulson@unit1127.com
License: UNKNOWN
Platform: UNKNOWN
